[{"revision": "0", "reference": "vk-bootstrap/0.4", "is_ref": true, "display_name": "vk-bootstrap/0.4", "id": "0139e9e754932c21dabf39df42fc1b484134ceb9", "build_id": null, "context": "host", "remote": {"name": "conancenter", "url": "https://center.conan.io"}, "url": "https://github.com/conan-io/conan-center-index", "homepage": "https://github.com/charles-lunarg/vk-bootstrap", "license": ["MIT"], "description": "Vulkan bootstraping library.", "topics": ["conan", "vk-bootstrap", "vulkan"], "provides": ["vk-bootstrap"], "recipe": "Downloaded", "package_revision": null, "binary": "Missing", "binary_remote": "conancenter", "creation_date": "2021-08-03 02:23:06 UTC", "requires": ["vulkan-headers/1.2.184"]}, {"revision": "0", "reference": "vulkan-headers/1.2.184", "is_ref": true, "display_name": "vulkan-headers/1.2.184", "id": "5ab84d6acfe1f23c4fae0ab88f26e3a396351ac9", "build_id": null, "context": "host", "remote": {"name": "conancenter", "url": "https://center.conan.io"}, "url": "https://github.com/conan-io/conan-center-index", "homepage": "https://github.com/KhronosGroup/Vulkan-Headers", "license": ["Apache-2.0"], "description": "Vulkan Header files.", "topics": ["vulkan-headers", "vulkan"], "provides": ["vulkan-headers"], "recipe": "Downloaded", "package_revision": "0", "binary": "Download", "binary_remote": "conancenter", "creation_date": "2021-11-29 14:55:16 UTC", "required_by": ["vk-bootstrap/0.4"]}]