[{"revision": "0", "reference": "fakeit/2.0.7", "is_ref": true, "display_name": "fakeit/2.0.7", "id": "23b9c2cf6d1b4ca0f3573ae9958ade93b1d14041", "build_id": null, "context": "host", "remote": {"name": "conancenter", "url": "https://center.conan.io"}, "url": "https://github.com/conan-io/conan-center-index", "homepage": "https://github.com/eranpeer/FakeIt", "license": ["MIT"], "description": "C++ mocking made easy. A simple yet very expressive, headers only library for c++ mocking.", "topics": ["mock", "fake", "spy"], "provides": ["fakeit"], "recipe": "Downloaded", "package_revision": null, "binary": "Missing", "binary_remote": "conancenter", "creation_date": "2021-03-24 21:33:31 UTC"}]