[{"revision": "0", "reference": "mpg123/1.26.4", "is_ref": true, "display_name": "mpg123/1.26.4", "id": "286bf6e50fb89d8d1a03d57ed6ab48b6486dee21", "build_id": null, "context": "host", "remote": {"name": "conancenter", "url": "https://center.conan.io"}, "url": "https://github.com/conan-io/conan-center-index", "homepage": "http://mpg123.org/", "license": ["LGPL-2.1-or-later", "GPL-2.0-or-later"], "description": "Fast console MPEG Audio Player and decoder library", "topics": ["conan", "mpg123", "mpeg", "audio", "player", "decoder"], "provides": ["mpg123"], "recipe": "Cache", "package_revision": null, "binary": "Missing", "binary_remote": "conancenter", "creation_date": "2021-07-21 00:58:52 UTC"}]