[{"revision": "0", "reference": "easyexif/1.0", "is_ref": true, "display_name": "easyexif/1.0", "id": "1aff124b71f6d938138ecd7179ff075f4304a85d", "build_id": null, "context": "host", "remote": {"name": "conancenter", "url": "https://center.conan.io"}, "url": "https://github.com/conan-io/conan-center-index", "homepage": "https://github.com/mayanklahiri/easyexif", "license": ["BSD-2-Clause"], "description": "Tiny ISO-compliant C++ EXIF parsing library, third-party dependency free.", "topics": ["conan", "exif", "image", "multimedia", "format", "graphics"], "provides": ["easyexif"], "recipe": "Downloaded", "package_revision": null, "binary": "Missing", "binary_remote": "conancenter", "creation_date": "2020-10-08 21:36:33 UTC"}]